{
    "abuseipdb_is_whitelisted": false,
    "abuseipdb_confidence_score": 100,
    "abuseipdb_country_code": "TW",
    "abuseipdb_isp": "Chunghwa Telecom Co. Ltd.",
    "abuseipdb_domain": "cht.com.tw",
    "abuseipdb_total_reports": 238,
    "abuseipdb_num_distinct_users": 79,
    "abuseipdb_last_reported_at": "2023-05-16T07:10:24+00:00",
    "virustotal_regional_internet_registry": "APNIC",
    "virustotal_as_owner": "Mobile Business Group",
    "virustotal_last_analysis_stats": {
        "harmless": 61,
        "malicious": 4,
        "suspicious": 2,
        "undetected": 20,
        "timeout": 0
    },
    "virustotal_asn": 17421,
    "virustotal_reputation": 0,
    "IBM_score": 1,
    "IBM_reason": "True",
    "IBM_reasonDescription": "True",
    "IBM_average history Score": 1.0,
    "IBM_most common score": 1,
    "SHODAN_asn": null,
    "SHODAN_isp": null,
    "SHODAN_vulns": "False",
    "ALIENVAULT_reputation": 0,
    "ALIENVAULT_false_positive": "False",
    "ALIENVAULT_asn": "AS17421 mobile business group"
}