{
    "abuseipdb_is_whitelisted": false,
    "abuseipdb_confidence_score": 100,
    "abuseipdb_country_code": "IR",
    "abuseipdb_isp": "Parsian High Tech Company PJSC",
    "abuseipdb_domain": "bertina.ir",
    "abuseipdb_total_reports": 236,
    "abuseipdb_num_distinct_users": 145,
    "abuseipdb_last_reported_at": "2023-05-19T02:23:28+00:00",
    "virustotal_regional_internet_registry": "RIPE NCC",
    "virustotal_as_owner": "Parsian High Tech Company PJSC",
    "virustotal_last_analysis_stats": {
        "harmless": 63,
        "malicious": 3,
        "suspicious": 1,
        "undetected": 20,
        "timeout": 0
    },
    "virustotal_asn": 42043,
    "virustotal_reputation": 0,
    "IBM_score": 1,
    "IBM_reason": "True",
    "IBM_reasonDescription": "True",
    "IBM_average history Score": 1.0,
    "IBM_most common score": 1,
    "SHODAN_asn": "AS42043",
    "SHODAN_isp": "Parsian High Tech Company PJSC",
    "SHODAN_vulns": "False",
    "ALIENVAULT_reputation": 0,
    "ALIENVAULT_false_positive": "False",
    "ALIENVAULT_asn": "AS42043 parsian high tech company pjsc"
}